{"id":"1dc3972a-0196-419e-b281-8af22a5f7f97","revision":0,"last_node_id":132,"last_link_id":195,"nodes":[{"id":113,"type":"Note","pos":[1182.3634033203125,6719.11669921875],"size":[210,159.49227905273438],"flags":{},"order":0,"mode":0,"inputs":[],"outputs":[],"properties":{"ue_properties":{"version":"7.0.1","widget_ue_connectable":{}},"widget_ue_connectable":{}},"widgets_values":["480p：16:9≈分辨率为 854×480 像素\n480p：1：1分辨率为 640×640 像素\n\n720p：16：9分辨率为 1280×720 像素\n720p：1：1分辨率为 960×960 像素"],"color":"#432","bgcolor":"#653"},{"id":52,"type":"VAELoader","pos":[1918.126220703125,6896.2880859375],"size":[360,82],"flags":{},"order":1,"mode":0,"inputs":[{"label":"vae_name","localized_name":"vae名称","name":"vae_name","type":"COMBO","widget":{"name":"vae_name"}}],"outputs":[{"label":"VAE","localized_name":"VAE","name":"VAE","type":"VAE","slot_index":0,"links":[64,79]}],"properties":{"cnr_id":"comfy-core","ver":"0.3.56","Node name for S&R":"VAELoader","ue_properties":{"version":"7.0.1","widget_ue_connectable":{}},"widget_ue_connectable":{"vae_name":true}},"widgets_values":["wan_2.1_vae.safetensors",null],"color":"#223","bgcolor":"#335"},{"id":94,"type":"Wan22PromptSelector","pos":[1400.166748046875,5883.56884765625],"size":[291.5181579589844,298],"flags":{},"order":2,"mode":0,"inputs":[{"label":"场景类型","localized_name":"场景类型","name":"场景类型","type":"COMBO","widget":{"name":"场景类型"},"link":null},{"label":"运动场景","localized_name":"运动场景","name":"运动场景","type":"COMBO","widget":{"name":"运动场景"},"link":null},{"label":"人物情绪","localized_name":"人物情绪","name":"人物情绪","type":"COMBO","widget":{"name":"人物情绪"},"link":null},{"label":"运镜方式","localized_name":"运镜方式","name":"运镜方式","type":"COMBO","widget":{"name":"运镜方式"},"link":null},{"label":"光源类型","localized_name":"光源类型","name":"光源类型","type":"COMBO","widget":{"name":"光源类型"},"link":null},{"label":"光线类型","localized_name":"光线类型","name":"光线类型","type":"COMBO","widget":{"name":"光线类型"},"link":null},{"label":"镜头类型","localized_name":"镜头类型","name":"镜头类型","type":"COMBO","widget":{"name":"镜头类型"},"link":null},{"label":"焦距","localized_name":"焦距","name":"焦距","type":"COMBO","widget":{"name":"焦距"},"link":null},{"label":"色调","localized_name":"色调","name":"色调","type":"COMBO","widget":{"name":"色调"},"link":null},{"label":"视觉风格","localized_name":"视觉风格","name":"视觉风格","type":"COMBO","widget":{"name":"视觉风格"},"link":null},{"label":"特效镜头","localized_name":"特效镜头","name":"特效镜头","type":"COMBO","widget":{"name":"特效镜头"},"link":null}],"outputs":[{"label":"提示词","localized_name":"提示词","name":"提示词","type":"STRING","links":null}],"properties":{"Node name for S&R":"Wan22PromptSelector","ue_properties":{"version":"7.0.1","widget_ue_connectable":{"场景类型":true,"运动场景":true,"人物情绪":true,"运镜方式":true,"光源类型":true,"光线类型":true,"镜头类型":true,"焦距":true,"色调":true,"视觉风格":true,"特效镜头":true}},"widget_ue_connectable":{"场景类型":true,"运动场景":true,"人物情绪":true,"运镜方式":true,"光源类型":true,"光线类型":true,"镜头类型":true,"焦距":true,"色调":true,"视觉风格":true,"特效镜头":true}},"widgets_values":["——","——","——","镜头推进","——","——","——","——","——","——","——"]},{"id":99,"type":"Note","pos":[1535.5130615234375,6835.62744140625],"size":[298.1592102050781,104.29852294921875],"flags":{},"order":3,"mode":0,"inputs":[],"outputs":[],"properties":{"ue_properties":{"version":"7.0.1","widget_ue_connectable":{}},"widget_ue_connectable":{}},"widgets_values":["WAN模型張數計算:\n官方工作流是fps：16\n秒數*FPS+1\n\n*張數可以計算到129張，這是別人測出來的有意義張數上限。搭配FPS 16也就是WAN 2.2可以最多算8秒的影片"],"color":"#432","bgcolor":"#653"},{"id":110,"type":"CLIPLoader","pos":[1361.282958984375,6290.396484375],"size":[398.328857421875,135.2608184814453],"flags":{},"order":4,"mode":0,"inputs":[{"label":"clip_name","localized_name":"CLIP名称","name":"clip_name","type":"COMBO","widget":{"name":"clip_name"},"link":null},{"label":"type","localized_name":"类型","name":"type","type":"COMBO","widget":{"name":"type"},"link":null},{"label":"device","localized_name":"设备","name":"device","shape":7,"type":"COMBO","widget":{"name":"device"},"link":null}],"outputs":[{"label":"CLIP","localized_name":"CLIP","name":"CLIP","type":"CLIP","slot_index":0,"links":[160,161]}],"properties":{"cnr_id":"comfy-core","ver":"0.3.56","Node name for S&R":"CLIPLoader","ue_properties":{"version":"7.0.1","widget_ue_connectable":{}},"widget_ue_connectable":{"clip_name":true,"type":true,"device":true}},"widgets_values":["umt5_xxl_fp8_e4m3fn_scaled.safetensors","wan","default",null],"color":"#223","bgcolor":"#335"},{"id":116,"type":"PathchSageAttentionKJ","pos":[2328.901123046875,4414.96533203125],"size":[218.17535400390625,58],"flags":{"collapsed":false},"order":27,"mode":0,"inputs":[{"label":"model","localized_name":"model","name":"model","type":"MODEL","link":167},{"label":"sage_attention","localized_name":"sage_attention","name":"sage_attention","type":"COMBO","widget":{"name":"sage_attention"},"link":null}],"outputs":[{"label":"MODEL","localized_name":"模型","name":"MODEL","type":"MODEL","links":[172]}],"properties":{"cnr_id":"comfyui-kjnodes","ver":"a6b867b63a29ca48ddb15c589e17a9f2d8530d57","Node name for S&R":"PathchSageAttentionKJ","ue_properties":{"version":"7.0.1","widget_ue_connectable":{"sage_attention":true}},"widget_ue_connectable":{"sage_attention":true}},"widgets_values":["auto"]},{"id":63,"type":"VAEDecode","pos":[3256.3447265625,5536.21337890625],"size":[210,46],"flags":{},"order":31,"mode":0,"inputs":[{"label":"Latent","localized_name":"Latent","name":"samples","type":"LATENT","link":140},{"label":"VAE","localized_name":"vae","name":"vae","type":"VAE","link":64}],"outputs":[{"label":"图像","localized_name":"图像","name":"IMAGE","type":"IMAGE","slot_index":0,"links":[101]}],"properties":{"cnr_id":"comfy-core","ver":"0.3.56","Node name for S&R":"VAEDecode","ue_properties":{"version":"7.0.1","widget_ue_connectable":{}},"widget_ue_connectable":{}},"widgets_values":[]},{"id":98,"type":"GetImageSizeAndCount","pos":[1163.0333251953125,6522.1875],"size":[277.20001220703125,86],"flags":{},"order":15,"mode":0,"inputs":[{"label":"图像","localized_name":"image","name":"image","type":"IMAGE","link":124}],"outputs":[{"label":"图像","localized_name":"image","name":"image","type":"IMAGE","links":[163]},{"label":"宽度","localized_name":"width","name":"width","type":"INT","links":[164]},{"label":"高度","localized_name":"height","name":"height","type":"INT","links":[165]},{"label":"数量","localized_name":"count","name":"count","type":"INT","links":[]}],"properties":{"cnr_id":"comfyui-kjnodes","ver":"2aa4da0f587f68c1c255b0152ed8f5c334ebe4b4","Node name for S&R":"GetImageSizeAndCount","ttNbgOverride":{"bgcolor":"#335","groupcolor":"#88A","color":"#223"},"ue_properties":{"version":"7.0.1","widget_ue_connectable":{}},"widget_ue_connectable":{}},"widgets_values":[],"color":"#223","bgcolor":"#335"},{"id":121,"type":"SetNode","pos":[2435.151611328125,6170.82373046875],"size":[210,60],"flags":{},"order":16,"mode":0,"inputs":[{"name":"CONDITIONING","type":"CONDITIONING","link":176}],"outputs":[{"label":"输出","name":"*","type":"*","links":null}],"properties":{"previousName":"条件-","ue_properties":{"version":"7.0.1","widget_ue_connectable":{}},"widget_ue_connectable":{}},"widgets_values":["条件-"],"color":"#332922","bgcolor":"#593930"},{"id":74,"type":"WanImageToVideo","pos":[2477.838623046875,6340.0185546875],"size":[342.5999755859375,210],"flags":{},"order":19,"mode":0,"inputs":[{"label":"positive","localized_name":"正面","name":"positive","type":"CONDITIONING","link":77},{"label":"negative","localized_name":"负面","name":"negative","type":"CONDITIONING","link":78},{"label":"vae","localized_name":"vae","name":"vae","type":"VAE","link":79},{"label":"clip_vision_output","localized_name":"clip视觉输出","name":"clip_vision_output","shape":7,"type":"CLIP_VISION_OUTPUT"},{"label":"start_image","localized_name":"开始图像","name":"start_image","shape":7,"type":"IMAGE","link":163},{"label":"width","localized_name":"宽度","name":"width","type":"INT","widget":{"name":"width"},"link":164},{"label":"height","localized_name":"高度","name":"height","type":"INT","widget":{"name":"height"},"link":165},{"label":"length","localized_name":"长度","name":"length","type":"INT","widget":{"name":"length"},"link":83},{"label":"batch_size","localized_name":"批量大小","name":"batch_size","type":"INT","widget":{"name":"batch_size"}}],"outputs":[{"label":"positive","localized_name":"正面","name":"positive","type":"CONDITIONING","slot_index":0,"links":[149]},{"label":"negative","localized_name":"负面","name":"negative","type":"CONDITIONING","slot_index":1,"links":[150]},{"label":"latent","localized_name":"潜在","name":"latent","type":"LATENT","slot_index":2,"links":[151]}],"properties":{"cnr_id":"comfy-core","ver":"0.3.56","Node name for S&R":"WanImageToVideo","ue_properties":{"version":"7.0.1","widget_ue_connectable":{}},"widget_ue_connectable":{"width":true,"height":true,"length":true,"batch_size":true}},"widgets_values":[1280,720,81,1]},{"id":124,"type":"TorchCompileModelWanVideoV2","pos":[2312.15380859375,4683.15234375],"size":[342.74609375,178],"flags":{},"order":22,"mode":0,"inputs":[{"label":"model","localized_name":"model","name":"model","type":"MODEL","link":195},{"label":"backend","localized_name":"backend","name":"backend","type":"COMBO","widget":{"name":"backend"},"link":null},{"label":"fullgraph","localized_name":"fullgraph","name":"fullgraph","type":"BOOLEAN","widget":{"name":"fullgraph"},"link":null},{"label":"mode","localized_name":"mode","name":"mode","type":"COMBO","widget":{"name":"mode"},"link":null},{"label":"dynamic","localized_name":"dynamic","name":"dynamic","type":"BOOLEAN","widget":{"name":"dynamic"},"link":null},{"label":"compile_transformer_blocks_only","localized_name":"compile_transformer_blocks_only","name":"compile_transformer_blocks_only","type":"BOOLEAN","widget":{"name":"compile_transformer_blocks_only"},"link":null},{"label":"dynamo_cache_size_limit","localized_name":"dynamo_cache_size_limit","name":"dynamo_cache_size_limit","type":"INT","widget":{"name":"dynamo_cache_size_limit"},"link":null}],"outputs":[{"label":"MODEL","localized_name":"模型","name":"MODEL","type":"MODEL","links":[180]}],"properties":{"cnr_id":"comfyui-kjnodes","ver":"a6b867b63a29ca48ddb15c589e17a9f2d8530d57","Node name for S&R":"TorchCompileModelWanVideoV2","ue_properties":{"version":"7.0.1","widget_ue_connectable":{"backend":true,"fullgraph":true,"mode":true,"dynamic":true,"compile_transformer_blocks_only":true,"dynamo_cache_size_limit":true}},"widget_ue_connectable":{"backend":true,"fullgraph":true,"mode":true,"dynamic":true,"compile_transformer_blocks_only":true,"dynamo_cache_size_limit":true}},"widgets_values":["inductor",false,"default",false,true,128]},{"id":120,"type":"ModelPatchTorchSettings","pos":[1974.2706298828125,4415.79736328125],"size":[247.443359375,58],"flags":{},"order":25,"mode":0,"inputs":[{"label":"model","localized_name":"model","name":"model","type":"MODEL","link":171},{"label":"enable_fp16_accumulation","localized_name":"enable_fp16_accumulation","name":"enable_fp16_accumulation","type":"BOOLEAN","widget":{"name":"enable_fp16_accumulation"},"link":null}],"outputs":[{"label":"MODEL","localized_name":"模型","name":"MODEL","type":"MODEL","links":[167]}],"properties":{"cnr_id":"comfyui-kjnodes","ver":"331260d90840187364e4bf17671bdc361085d606","Node name for S&R":"ModelPatchTorchSettings","ue_properties":{"version":"7.0.1","widget_ue_connectable":{"enable_fp16_accumulation":true}},"widget_ue_connectable":{"enable_fp16_accumulation":true}},"widgets_values":[true]},{"id":112,"type":"EasyCache","pos":[2768.1943359375,4797.11767578125],"size":[270,130],"flags":{},"order":28,"mode":0,"inputs":[{"label":"model","localized_name":"model","name":"model","type":"MODEL","link":187},{"label":"reuse_threshold","localized_name":"reuse_threshold","name":"reuse_threshold","type":"FLOAT","widget":{"name":"reuse_threshold"},"link":null},{"label":"start_percent","localized_name":"start_percent","name":"start_percent","type":"FLOAT","widget":{"name":"start_percent"},"link":null},{"label":"end_percent","localized_name":"end_percent","name":"end_percent","type":"FLOAT","widget":{"name":"end_percent"},"link":null},{"label":"verbose","localized_name":"verbose","name":"verbose","type":"BOOLEAN","widget":{"name":"verbose"},"link":null}],"outputs":[{"label":"MODEL","localized_name":"模型","name":"MODEL","type":"MODEL","links":[155]}],"properties":{"cnr_id":"comfy-core","ver":"0.3.59","Node name for S&R":"EasyCache","ue_properties":{"version":"7.0.1","widget_ue_connectable":{"reuse_threshold":true,"start_percent":true,"end_percent":true,"verbose":true}},"widget_ue_connectable":{"reuse_threshold":true,"start_percent":true,"end_percent":true,"verbose":true}},"widgets_values":[0.1,0,0.95,false]},{"id":111,"type":"EasyCache","pos":[2763.10546875,4261.04296875],"size":[270,130],"flags":{},"order":29,"mode":0,"inputs":[{"label":"model","localized_name":"model","name":"model","type":"MODEL","link":172},{"label":"reuse_threshold","localized_name":"reuse_threshold","name":"reuse_threshold","type":"FLOAT","widget":{"name":"reuse_threshold"},"link":null},{"label":"start_percent","localized_name":"start_percent","name":"start_percent","type":"FLOAT","widget":{"name":"start_percent"},"link":null},{"label":"end_percent","localized_name":"end_percent","name":"end_percent","type":"FLOAT","widget":{"name":"end_percent"},"link":null},{"label":"verbose","localized_name":"verbose","name":"verbose","type":"BOOLEAN","widget":{"name":"verbose"},"link":null}],"outputs":[{"label":"MODEL","localized_name":"模型","name":"MODEL","type":"MODEL","links":[153]}],"properties":{"cnr_id":"comfy-core","ver":"0.3.59","Node name for S&R":"EasyCache","ue_properties":{"version":"7.0.1","widget_ue_connectable":{"reuse_threshold":true,"start_percent":true,"end_percent":true,"verbose":true}},"widget_ue_connectable":{"reuse_threshold":true,"start_percent":true,"end_percent":true,"verbose":true}},"widgets_values":[0.1,0.15,1,false]},{"id":69,"type":"JWInteger","pos":[1534.302734375,6725.90869140625],"size":[315,58],"flags":{},"order":5,"mode":0,"inputs":[{"label":"value","localized_name":"value","name":"value","type":"INT","widget":{"name":"value"}}],"outputs":[{"label":"INT","localized_name":"整数","name":"INT","type":"INT","links":[83]}],"properties":{"cnr_id":"jameswalker-nodes","ver":"5bd85aaf7616878471469c4ec7e11bbd0cef3bf2","Node name for S&R":"JWInteger","ue_properties":{"version":"7.0.1","widget_ue_connectable":{}},"widget_ue_connectable":{"value":true}},"widgets_values":[65]},{"id":62,"type":"VHS_VideoCombine","pos":[3339.18896484375,5686.6806640625],"size":[328.4435119628906,521.4994506835938],"flags":{},"order":32,"mode":0,"inputs":[{"label":"图像","localized_name":"images","name":"images","type":"IMAGE","link":101},{"label":"音频","localized_name":"audio","name":"audio","shape":7,"type":"AUDIO"},{"label":"批次管理","localized_name":"meta_batch","name":"meta_batch","shape":7,"type":"VHS_BatchManager"},{"label":"vae","localized_name":"vae","name":"vae","shape":7,"type":"VAE","link":null},{"label":"frame_rate","localized_name":"帧率","name":"frame_rate","type":"FLOAT","widget":{"name":"frame_rate"}},{"label":"loop_count","localized_name":"循环次数","name":"loop_count","type":"INT","widget":{"name":"loop_count"}},{"label":"filename_prefix","localized_name":"文件名前缀","name":"filename_prefix","type":"STRING","widget":{"name":"filename_prefix"}},{"label":"format","localized_name":"格式","name":"format","type":"COMBO","widget":{"name":"format"}},{"label":"pingpong","localized_name":"Ping-Pong","name":"pingpong","type":"BOOLEAN","widget":{"name":"pingpong"}},{"label":"save_output","localized_name":"保存到输出文件夹","name":"save_output","type":"BOOLEAN","widget":{"name":"save_output"}},{"name":"pix_fmt","type":["yuv420p","yuv420p10le"],"widget":{"name":"pix_fmt"},"link":null},{"name":"crf","type":"INT","widget":{"name":"crf"},"link":null},{"label":"保存元数据","localized_name":"保存元数据","name":"save_metadata","type":"BOOLEAN","widget":{"name":"save_metadata"},"link":null},{"name":"trim_to_audio","type":"BOOLEAN","widget":{"name":"trim_to_audio"},"link":null}],"outputs":[{"label":"文件名","localized_name":"Filenames","name":"Filenames","type":"VHS_FILENAMES"}],"properties":{"cnr_id":"comfyui-videohelpersuite","ver":"4c7858ddd5126f7293dc3c9f6e0fc4c263cde079","Node name for S&R":"VHS_VideoCombine","ue_properties":{"version":"7.0.1","widget_ue_connectable":{}},"widget_ue_connectable":{"frame_rate":true,"loop_count":true,"filename_prefix":true,"format":true,"pingpong":true,"save_output":true,"pix_fmt":true,"crf":true,"save_metadata":true,"trim_to_audio":true}},"widgets_values":{"frame_rate":16,"loop_count":0,"filename_prefix":"AnimateDiff","format":"video/h264-mp4","pix_fmt":"yuv420p","crf":19,"save_metadata":true,"trim_to_audio":false,"pingpong":false,"save_output":true,"videopreview":{"paused":false,"hidden":false,"params":{"filename":"AnimateDiff_00103.mp4","workflow":"AnimateDiff_00103.png","fullpath":"C:\\ComfyUI_Max\\ComfyUI\\output\\AnimateDiff_00103.mp4","format":"video/h264-mp4","subfolder":"","type":"output","frame_rate":16}}}},{"id":109,"type":"WanMoeKSampler","pos":[2918.341796875,5480.90966796875],"size":[270,566],"flags":{},"order":30,"mode":0,"inputs":[{"label":"model_high_noise","localized_name":"model_high_noise","name":"model_high_noise","type":"MODEL","link":153},{"label":"model_low_noise","localized_name":"model_low_noise","name":"model_low_noise","type":"MODEL","link":155},{"label":"positive","localized_name":"positive","name":"positive","type":"CONDITIONING","link":149},{"label":"negative","localized_name":"negative","name":"negative","type":"CONDITIONING","link":150},{"label":"latent_image","localized_name":"latent_image","name":"latent_image","type":"LATENT","link":151},{"label":"boundary","localized_name":"boundary","name":"boundary","type":"FLOAT","widget":{"name":"boundary"},"link":null},{"label":"seed","localized_name":"seed","name":"seed","type":"INT","widget":{"name":"seed"},"link":null},{"label":"steps","localized_name":"steps","name":"steps","type":"INT","widget":{"name":"steps"},"link":null},{"label":"cfg_high_noise","localized_name":"cfg_high_noise","name":"cfg_high_noise","type":"FLOAT","widget":{"name":"cfg_high_noise"},"link":null},{"label":"cfg_low_noise","localized_name":"cfg_low_noise","name":"cfg_low_noise","type":"FLOAT","widget":{"name":"cfg_low_noise"},"link":null},{"label":"sampler_name","localized_name":"sampler_name","name":"sampler_name","type":"COMBO","widget":{"name":"sampler_name"},"link":null},{"label":"scheduler","localized_name":"scheduler","name":"scheduler","type":"COMBO","widget":{"name":"scheduler"},"link":null},{"label":"sigma_shift","localized_name":"sigma_shift","name":"sigma_shift","type":"FLOAT","widget":{"name":"sigma_shift"},"link":null},{"label":"denoise","localized_name":"denoise","name":"denoise","type":"FLOAT","widget":{"name":"denoise"},"link":null}],"outputs":[{"label":"LATENT","localized_name":"Latent","name":"LATENT","type":"LATENT","links":[140]}],"properties":{"aux_id":"stduhpf/ComfyUI-WanMoeKSampler","ver":"8fc990069a69175b1f64c0dc84acbacf71682a9b","Node name for S&R":"WanMoeKSampler","ue_properties":{"version":"7.0.1","widget_ue_connectable":{"boundary":true,"seed":true,"steps":true,"cfg_high_noise":true,"cfg_low_noise":true,"sampler_name":true,"scheduler":true,"sigma_shift":true,"denoise":true}},"widget_ue_connectable":{"boundary":true,"seed":true,"steps":true,"cfg_high_noise":true,"cfg_low_noise":true,"sampler_name":true,"scheduler":true,"sigma_shift":true,"denoise":true}},"widgets_values":[0.9,432617925254680,"randomize",8,1,1,"euler","simple",8,1]},{"id":51,"type":"CLIPTextEncode","pos":[1875.324951171875,6209.54052734375],"size":[425.27801513671875,180.6060791015625],"flags":{},"order":11,"mode":0,"inputs":[{"label":"CLIP","localized_name":"clip","name":"clip","type":"CLIP","link":160},{"label":"text","localized_name":"文本","name":"text","type":"STRING","widget":{"name":"text"}}],"outputs":[{"label":"条件","localized_name":"条件","name":"CONDITIONING","type":"CONDITIONING","slot_index":0,"links":[78,176]}],"properties":{"cnr_id":"comfy-core","ver":"0.3.56","Node name for S&R":"CLIPTextEncode","ue_properties":{"version":"7.0.1","widget_ue_connectable":{}},"widget_ue_connectable":{"text":true}},"widgets_values":["镜头环绕，灯具频闪，灯具关闭，镜头旋转，标志，logo，水印，文字，英文，单词，画面杂乱，色调艳丽，过曝，静态，细节模糊不清，字幕，风格，作品，画作，画面，静止，整体发灰，最差质量，低质量，JPEG压缩残留，丑陋的，残缺的，多余的手指，画得不好的手部，画得不好的脸部，畸形的，毁容的，形态畸形的肢体，手指融合，静止不动的画面，杂乱的背景，三条腿，背景人很多，倒着走",[false,true]],"color":"#322","bgcolor":"#533"},{"id":108,"type":"UnetLoaderGGUF","pos":[554.4217529296875,4838.40478515625],"size":[453.5385437011719,79.67610168457031],"flags":{},"order":6,"mode":0,"inputs":[{"label":"unet_name","localized_name":"unet_name","name":"unet_name","type":"COMBO","widget":{"name":"unet_name"},"link":null}],"outputs":[{"label":"MODEL","localized_name":"模型","name":"MODEL","type":"MODEL","links":[191]}],"properties":{"Node name for S&R":"UnetLoaderGGUF","cnr_id":"comfyui-gguf","ver":"1.1.3","ue_properties":{"version":"7.0.1","widget_ue_connectable":{}},"widget_ue_connectable":{"unet_name":true}},"widgets_values":["wan2.2_i2v_low_noise_14B_Q8_0.gguf"]},{"id":107,"type":"UnetLoaderGGUF","pos":[522.408447265625,4155.181640625],"size":[453.5385437011719,79.67610168457031],"flags":{},"order":7,"mode":0,"inputs":[{"label":"unet_name","localized_name":"unet_name","name":"unet_name","type":"COMBO","widget":{"name":"unet_name"},"link":null}],"outputs":[{"label":"MODEL","localized_name":"模型","name":"MODEL","type":"MODEL","links":[190]}],"properties":{"Node name for S&R":"UnetLoaderGGUF","cnr_id":"comfyui-gguf","ver":"1.1.3","ue_properties":{"version":"7.0.1","widget_ue_connectable":{}},"widget_ue_connectable":{"unet_name":true}},"widgets_values":["wan2.2_i2v_high_noise_14B_Q8_0.gguf"]},{"id":73,"type":"LoraLoaderModelOnly","pos":[1031.77587890625,4147.99755859375],"size":[554.6221923828125,144.86941528320312],"flags":{},"order":14,"mode":0,"inputs":[{"label":"模型","localized_name":"模型","name":"model","type":"MODEL","link":190},{"label":"lora_name","localized_name":"LoRA名称","name":"lora_name","type":"COMBO","widget":{"name":"lora_name"}},{"label":"strength_model","localized_name":"模型强度","name":"strength_model","type":"FLOAT","widget":{"name":"strength_model"}}],"outputs":[{"label":"模型","localized_name":"模型","name":"MODEL","type":"MODEL","links":[175]}],"properties":{"cnr_id":"comfy-core","ver":"0.3.56","Node name for S&R":"LoraLoaderModelOnly","ue_properties":{"version":"7.0.1","widget_ue_connectable":{}},"widget_ue_connectable":{"lora_name":true,"strength_model":true}},"widgets_values":["wan\\Wan2.2-Lightning_T2V-A14B-4steps-lora_HIGH_fp16_KJ.safetensors",1,null]},{"id":117,"type":"WanVideoNAG","pos":[1859.8076171875,4095.39208984375],"size":[270,150],"flags":{},"order":18,"mode":0,"inputs":[{"label":"model","localized_name":"model","name":"model","type":"MODEL","link":175},{"label":"conditioning","localized_name":"conditioning","name":"conditioning","type":"CONDITIONING","link":168},{"label":"nag_scale","localized_name":"nag_scale","name":"nag_scale","type":"FLOAT","widget":{"name":"nag_scale"},"link":null},{"label":"nag_alpha","localized_name":"nag_alpha","name":"nag_alpha","type":"FLOAT","widget":{"name":"nag_alpha"},"link":null},{"label":"nag_tau","localized_name":"nag_tau","name":"nag_tau","type":"FLOAT","widget":{"name":"nag_tau"},"link":null},{"label":"input_type","localized_name":"input_type","name":"input_type","shape":7,"type":"COMBO","widget":{"name":"input_type"},"link":null}],"outputs":[{"label":"model","localized_name":"model","name":"model","type":"MODEL","links":[192]}],"properties":{"cnr_id":"comfyui-kjnodes","ver":"a6b867b63a29ca48ddb15c589e17a9f2d8530d57","Node name for S&R":"WanVideoNAG","ue_properties":{"version":"7.0.1","widget_ue_connectable":{"nag_scale":true,"nag_alpha":true,"nag_tau":true,"input_type":true}},"widget_ue_connectable":{"nag_scale":true,"nag_alpha":true,"nag_tau":true,"input_type":true}},"widgets_values":[11,0.25,2.5,"default"]},{"id":115,"type":"TorchCompileModelWanVideoV2","pos":[2363.2470703125,4118.6904296875],"size":[342.74609375,178],"flags":{},"order":23,"mode":0,"inputs":[{"label":"model","localized_name":"model","name":"model","type":"MODEL","link":193},{"label":"backend","localized_name":"backend","name":"backend","type":"COMBO","widget":{"name":"backend"},"link":null},{"label":"fullgraph","localized_name":"fullgraph","name":"fullgraph","type":"BOOLEAN","widget":{"name":"fullgraph"},"link":null},{"label":"mode","localized_name":"mode","name":"mode","type":"COMBO","widget":{"name":"mode"},"link":null},{"label":"dynamic","localized_name":"dynamic","name":"dynamic","type":"BOOLEAN","widget":{"name":"dynamic"},"link":null},{"label":"compile_transformer_blocks_only","localized_name":"compile_transformer_blocks_only","name":"compile_transformer_blocks_only","type":"BOOLEAN","widget":{"name":"compile_transformer_blocks_only"},"link":null},{"label":"dynamo_cache_size_limit","localized_name":"dynamo_cache_size_limit","name":"dynamo_cache_size_limit","type":"INT","widget":{"name":"dynamo_cache_size_limit"},"link":null}],"outputs":[{"label":"MODEL","localized_name":"模型","name":"MODEL","type":"MODEL","links":[171]}],"properties":{"cnr_id":"comfyui-kjnodes","ver":"a6b867b63a29ca48ddb15c589e17a9f2d8530d57","Node name for S&R":"TorchCompileModelWanVideoV2","ue_properties":{"version":"7.0.1","widget_ue_connectable":{"backend":true,"fullgraph":true,"mode":true,"dynamic":true,"compile_transformer_blocks_only":true,"dynamo_cache_size_limit":true}},"widget_ue_connectable":{"backend":true,"fullgraph":true,"mode":true,"dynamic":true,"compile_transformer_blocks_only":true,"dynamo_cache_size_limit":true}},"widgets_values":["inductor",false,"default",false,true,128]},{"id":131,"type":"CFGZeroStar","pos":[2153.89111328125,4140.6435546875],"size":[159.744140625,26],"flags":{},"order":21,"mode":0,"inputs":[{"label":"model","localized_name":"model","name":"model","type":"MODEL","link":192}],"outputs":[{"label":"patched_model","localized_name":"patched_model","name":"patched_model","type":"MODEL","links":[193]}],"properties":{"cnr_id":"comfy-core","ver":"0.3.49","Node name for S&R":"CFGZeroStar","widget_ue_connectable":{},"ue_properties":{"version":"7.0.1","widget_ue_connectable":{}}},"widgets_values":[]},{"id":75,"type":"LoraLoaderModelOnly","pos":[1086.464111328125,4713.18310546875],"size":[567.418701171875,133.9775848388672],"flags":{},"order":13,"mode":0,"inputs":[{"label":"模型","localized_name":"模型","name":"model","type":"MODEL","link":191},{"label":"lora_name","localized_name":"LoRA名称","name":"lora_name","type":"COMBO","widget":{"name":"lora_name"}},{"label":"strength_model","localized_name":"模型强度","name":"strength_model","type":"FLOAT","widget":{"name":"strength_model"}}],"outputs":[{"label":"模型","localized_name":"模型","name":"MODEL","type":"MODEL","links":[186]}],"properties":{"cnr_id":"comfy-core","ver":"0.3.56","Node name for S&R":"LoraLoaderModelOnly","ue_properties":{"version":"7.0.1","widget_ue_connectable":{}},"widget_ue_connectable":{"lora_name":true,"strength_model":true}},"widgets_values":["wan\\Wan2.2-Lightning_T2V-A14B-4steps-lora_LOW_fp16_KJ.safetensors",1,null]},{"id":123,"type":"GetNode","pos":[1505.2642822265625,4917.779296875],"size":[210,58],"flags":{},"order":8,"mode":0,"inputs":[],"outputs":[{"name":"CONDITIONING","type":"CONDITIONING","links":[178]}],"properties":{"ue_properties":{"version":"7.0.1","widget_ue_connectable":{}},"widget_ue_connectable":{}},"widgets_values":["条件-"],"color":"#332922","bgcolor":"#593930"},{"id":122,"type":"WanVideoNAG","pos":[1734.7506103515625,4692.779296875],"size":[270,150],"flags":{},"order":17,"mode":0,"inputs":[{"label":"model","localized_name":"model","name":"model","type":"MODEL","link":186},{"label":"conditioning","localized_name":"conditioning","name":"conditioning","type":"CONDITIONING","link":178},{"label":"nag_scale","localized_name":"nag_scale","name":"nag_scale","type":"FLOAT","widget":{"name":"nag_scale"},"link":null},{"label":"nag_alpha","localized_name":"nag_alpha","name":"nag_alpha","type":"FLOAT","widget":{"name":"nag_alpha"},"link":null},{"label":"nag_tau","localized_name":"nag_tau","name":"nag_tau","type":"FLOAT","widget":{"name":"nag_tau"},"link":null},{"label":"input_type","localized_name":"input_type","name":"input_type","shape":7,"type":"COMBO","widget":{"name":"input_type"},"link":null}],"outputs":[{"label":"model","localized_name":"model","name":"model","type":"MODEL","links":[194]}],"properties":{"cnr_id":"comfyui-kjnodes","ver":"a6b867b63a29ca48ddb15c589e17a9f2d8530d57","Node name for S&R":"WanVideoNAG","ue_properties":{"version":"7.0.1","widget_ue_connectable":{"nag_scale":true,"nag_alpha":true,"nag_tau":true,"input_type":true}},"widget_ue_connectable":{"nag_scale":true,"nag_alpha":true,"nag_tau":true,"input_type":true}},"widgets_values":[11,0.25,2.5,"default"]},{"id":132,"type":"CFGZeroStar","pos":[2075.300537109375,4683.39111328125],"size":[159.744140625,26],"flags":{},"order":20,"mode":0,"inputs":[{"label":"model","localized_name":"model","name":"model","type":"MODEL","link":194}],"outputs":[{"label":"patched_model","localized_name":"patched_model","name":"patched_model","type":"MODEL","links":[195]}],"properties":{"cnr_id":"comfy-core","ver":"0.3.49","Node name for S&R":"CFGZeroStar","widget_ue_connectable":{},"ue_properties":{"version":"7.0.1","widget_ue_connectable":{}}},"widgets_values":[]},{"id":125,"type":"ModelPatchTorchSettings","pos":[1980.5130615234375,4925.2138671875],"size":[247.443359375,58],"flags":{},"order":24,"mode":0,"inputs":[{"label":"model","localized_name":"model","name":"model","type":"MODEL","link":180},{"label":"enable_fp16_accumulation","localized_name":"enable_fp16_accumulation","name":"enable_fp16_accumulation","type":"BOOLEAN","widget":{"name":"enable_fp16_accumulation"},"link":null}],"outputs":[{"label":"MODEL","localized_name":"模型","name":"MODEL","type":"MODEL","links":[181]}],"properties":{"cnr_id":"comfyui-kjnodes","ver":"331260d90840187364e4bf17671bdc361085d606","Node name for S&R":"ModelPatchTorchSettings","ue_properties":{"version":"7.0.1","widget_ue_connectable":{"enable_fp16_accumulation":true}},"widget_ue_connectable":{"enable_fp16_accumulation":true}},"widgets_values":[true]},{"id":126,"type":"PathchSageAttentionKJ","pos":[2331.85498046875,4940.6494140625],"size":[218.17535400390625,58],"flags":{"collapsed":false},"order":26,"mode":0,"inputs":[{"label":"model","localized_name":"model","name":"model","type":"MODEL","link":181},{"label":"sage_attention","localized_name":"sage_attention","name":"sage_attention","type":"COMBO","widget":{"name":"sage_attention"},"link":null}],"outputs":[{"label":"MODEL","localized_name":"模型","name":"MODEL","type":"MODEL","links":[187]}],"properties":{"cnr_id":"comfyui-kjnodes","ver":"a6b867b63a29ca48ddb15c589e17a9f2d8530d57","Node name for S&R":"PathchSageAttentionKJ","ue_properties":{"version":"7.0.1","widget_ue_connectable":{"sage_attention":true}},"widget_ue_connectable":{"sage_attention":true}},"widgets_values":["auto"]},{"id":114,"type":"GetNode","pos":[1606.7261962890625,4236.314453125],"size":[210,58],"flags":{},"order":9,"mode":0,"inputs":[],"outputs":[{"name":"CONDITIONING","type":"CONDITIONING","links":[168]}],"properties":{"ue_properties":{"version":"7.0.1","widget_ue_connectable":{}},"widget_ue_connectable":{}},"widgets_values":["条件-"],"color":"#332922","bgcolor":"#593930"},{"id":70,"type":"CLIPTextEncode","pos":[1871.07373046875,5928.93896484375],"size":[428.84033203125,181.09986877441406],"flags":{},"order":12,"mode":0,"inputs":[{"label":"CLIP","localized_name":"clip","name":"clip","type":"CLIP","link":161},{"label":"text","localized_name":"文本","name":"text","type":"STRING","widget":{"name":"text"}}],"outputs":[{"label":"条件","localized_name":"条件","name":"CONDITIONING","type":"CONDITIONING","slot_index":0,"links":[77]}],"properties":{"cnr_id":"comfy-core","ver":"0.3.56","Node name for S&R":"CLIPTextEncode","ue_properties":{"version":"7.0.1","widget_ue_connectable":{}},"widget_ue_connectable":{"text":true}},"widgets_values":["吊灯一直亮着，镜头从远景到近景移动，镜头向前推进聚焦于吊灯。吊灯散发出温暖的光芒。镜头的移动使得吊灯的细节和光影效果得以充分展示。",[false,true]],"color":"#232","bgcolor":"#353"},{"id":54,"type":"LoadImage","pos":[519.2874755859375,6396.8505859375],"size":[450,540],"flags":{},"order":10,"mode":0,"inputs":[{"label":"image","localized_name":"图像","name":"image","type":"COMBO","widget":{"name":"image"}},{"label":"upload","localized_name":"选择文件上传","name":"upload","type":"IMAGEUPLOAD","widget":{"name":"upload"}}],"outputs":[{"label":"图像","localized_name":"图像","name":"IMAGE","type":"IMAGE","slot_index":0,"links":[124]},{"label":"遮罩","localized_name":"遮罩","name":"MASK","type":"MASK","slot_index":1}],"properties":{"cnr_id":"comfy-core","ver":"0.3.56","Node name for S&R":"LoadImage","ue_properties":{"version":"7.0.1","widget_ue_connectable":{}},"widget_ue_connectable":{"image":true,"upload":true}},"widgets_values":["视频扩图-2.jpg","image"]}],"links":[[64,52,0,63,1,"VAE"],[77,70,0,74,0,"CONDITIONING"],[78,51,0,74,1,"CONDITIONING"],[79,52,0,74,2,"VAE"],[83,69,0,74,7,"INT"],[101,63,0,62,0,"IMAGE"],[124,54,0,98,0,"IMAGE"],[140,109,0,63,0,"LATENT"],[149,74,0,109,2,"CONDITIONING"],[150,74,1,109,3,"CONDITIONING"],[151,74,2,109,4,"LATENT"],[153,111,0,109,0,"MODEL"],[155,112,0,109,1,"MODEL"],[160,110,0,51,0,"CLIP"],[161,110,0,70,0,"CLIP"],[163,98,0,74,4,"IMAGE"],[164,98,1,74,5,"INT"],[165,98,2,74,6,"INT"],[167,120,0,116,0,"MODEL"],[168,114,0,117,1,"CONDITIONING"],[171,115,0,120,0,"MODEL"],[172,116,0,111,0,"MODEL"],[175,73,0,117,0,"MODEL"],[176,51,0,121,0,"*"],[178,123,0,122,1,"CONDITIONING"],[180,124,0,125,0,"MODEL"],[181,125,0,126,0,"MODEL"],[186,75,0,122,0,"MODEL"],[187,126,0,112,0,"MODEL"],[190,107,0,73,0,"MODEL"],[191,108,0,75,0,"MODEL"],[192,117,0,131,0,"MODEL"],[193,131,0,115,0,"MODEL"],[194,122,0,132,0,"MODEL"],[195,132,0,124,0,"MODEL"]],"groups":[{"id":1,"title":"Group","bounding":[143.30926513671875,5170.08544921875,3860.3603515625,2043.3695068359375],"color":"#3f789e","font_size":24,"flags":{}},{"id":3,"title":"Group","bounding":[467.9217224121094,4003.003662109375,2184.504638671875,504.9623107910156],"color":"#3f789e","font_size":24,"flags":{}},{"id":4,"title":"Group","bounding":[501.5285949707031,4574.2666015625,2184.504638671875,504.9623107910156],"color":"#3f789e","font_size":24,"flags":{}}],"config":{},"extra":{"VHS_KeepIntermediate":true,"links_added_by_ue":[],"VHS_MetadataImage":true,"ue_links":[],"0246.VERSION":[0,0,4],"VHS_latentpreviewrate":0,"VHS_latentpreview":false,"ds":{"scale":0.9646149645000015,"offset":[-1371.1601354427087,-5717.143992638]},"frontendVersion":"1.23.0"},"version":0.4}